iotiumscraper/__init__.py
iotiumscraper/kastle.py
kastlelib/__init__.py
kastlelib/scrape_kastle.py
iotiumscraper-0.2.6.dist-info/METADATA
iotiumscraper-0.2.6.dist-info/WHEEL
iotiumscraper-0.2.6.dist-info/top_level.txt
iotiumscraper-0.2.6.dist-info/RECORD
