Metadata-Version: 2.1
Name: iotiumscraper
Version: 0.2.6
Summary: scrape data from kastle and push to postgres
Author: Raja
Requires-Dist: selenium
Requires-Dist: chromedriver-py
Requires-Dist: psycopg2
